binmao_libs/__init__.py
binmao_libs/config.py
binmao_libs/db.py
binmao_libs/hello.py
binmao_libs/https.py
binmao_libs/model.py
binmao_libs/oss.py
binmao_libs-1.2.1.dist-info/LICENSE
binmao_libs-1.2.1.dist-info/METADATA
binmao_libs-1.2.1.dist-info/WHEEL
binmao_libs-1.2.1.dist-info/top_level.txt
binmao_libs-1.2.1.dist-info/RECORD
