Metadata-Version: 2.1
Name: binmao-libs
Version: 1.2.1
Summary: binmao linbs
Author-email: chishijie <chishijie85@gmail.com>
Classifier: Programming Language :: Python :: 3
Classifier: License :: OSI Approved :: MIT License
Classifier: Operating System :: OS Independent
Requires-Python: >=3.10
License-File: LICENSE
Requires-Dist: flasgger >=0.9.7.1
Requires-Dist: Flask >=2.3.2
Requires-Dist: peewee >=3.16.3
Requires-Dist: prometheus-flask-exporter >=0.22.4
Requires-Dist: qiniu >=7.11.1
Requires-Dist: PyYAML >=6.0.1
